tiskitpy/__init__.py
tiskitpy/clean_rotator.py
tiskitpy/cleaned_stream.py
tiskitpy/logger.py
tiskitpy/time_spans.py
tiskitpy/version.py
tiskitpy/compliance/__init__.py
tiskitpy/compliance/_obspy_None_Description_example.py
tiskitpy/compliance/compliance.py
tiskitpy/compliance/earth_model.py
tiskitpy/data_cleaner/__init__.py
tiskitpy/data_cleaner/data_cleaner_tf.py
tiskitpy/data_cleaner/rf_list.py
tiskitpy/decimate/.DS_Store
tiskitpy/decimate/ToDo.md
tiskitpy/decimate/__init__.py
tiskitpy/decimate/decimator.py
tiskitpy/decimate/fir_filter.py
tiskitpy/decimate/version.py
tiskitpy/decimate/__pycache__/FIR_filter.cpython-38.pyc
tiskitpy/decimate/__pycache__/PSD.cpython-38.pyc
tiskitpy/decimate/__pycache__/Peterson_noise_model.cpython-38.pyc
tiskitpy/decimate/__pycache__/__init__.cpython-310.pyc
tiskitpy/decimate/__pycache__/__init__.cpython-38.pyc
tiskitpy/decimate/__pycache__/__init__.cpython-39.pyc
tiskitpy/decimate/__pycache__/coherence.cpython-38.pyc
tiskitpy/decimate/__pycache__/decimate.cpython-38.pyc
tiskitpy/decimate/__pycache__/decimate_SDS.cpython-38.pyc
tiskitpy/decimate/__pycache__/decimate_SDS.cpython-39.pyc
tiskitpy/decimate/__pycache__/decimator.cpython-310.pyc
tiskitpy/decimate/__pycache__/decimator.cpython-38.pyc
tiskitpy/decimate/__pycache__/decimator.cpython-39.pyc
tiskitpy/decimate/__pycache__/fir_filter.cpython-310.pyc
tiskitpy/decimate/__pycache__/fir_filter.cpython-39.pyc
tiskitpy/decimate/__pycache__/transfer_function.cpython-38.pyc
tiskitpy/decimate/__pycache__/utils.cpython-38.pyc
tiskitpy/decimate/sac_fir/dec2
tiskitpy/decimate/sac_fir/dec3
tiskitpy/decimate/sac_fir/dec4
tiskitpy/decimate/sac_fir/dec5
tiskitpy/decimate/sac_fir/dec6
tiskitpy/decimate/sac_fir/dec7
tiskitpy/fir_corr/__init__.py
tiskitpy/fir_corr/fir2caus.py
tiskitpy/functions/Peterson_noise_model.py
tiskitpy/functions/__init__.py
tiskitpy/functions/plot_compliance_stack.py
tiskitpy/functions/read_mseed.py
tiskitpy/functions/stream_synchronize.py
tiskitpy-2.1.0.dist-info/LICENSE.txt
tiskitpy-2.1.0.dist-info/METADATA
tiskitpy-2.1.0.dist-info/WHEEL
tiskitpy-2.1.0.dist-info/entry_points.txt
tiskitpy-2.1.0.dist-info/top_level.txt
tiskitpy-2.1.0.dist-info/RECORD
